dymoprint/__init__.py
dymoprint/_version.py
dymoprint/barcode_writer.py
dymoprint/command_line.py
dymoprint/constants.py
dymoprint/detect.py
dymoprint/dymo_print_engines.py
dymoprint/font_config.py
dymoprint/gui.py
dymoprint/labeler.py
dymoprint/metadata.py
dymoprint/q_dymo_label_widgets.py
dymoprint/q_dymo_labels_list.py
dymoprint/unicode_blocks.py
dymoprint/utils.py
dymoprint/resources/fonts/Carlito-Bold.ttf
dymoprint/resources/fonts/Carlito-BoldItalic.ttf
dymoprint/resources/fonts/Carlito-Italic.ttf
dymoprint/resources/fonts/Carlito-Regular.ttf
dymoprint/resources/fonts/LICENSE
dymoprint/resources/fonts/__init__.py
dymoprint/resources/icons/__init__.py
dymoprint/resources/icons/barcode_icon.png
dymoprint/resources/icons/barcode_text_icon.png
dymoprint/resources/icons/gui_icon.png
dymoprint/resources/icons/img_icon.png
dymoprint/resources/icons/qr_icon.png
dymoprint/resources/icons/txt_icon.png
dymoprint-2.5.0.dist-info/METADATA
dymoprint-2.5.0.dist-info/WHEEL
dymoprint-2.5.0.dist-info/entry_points.txt
dymoprint-2.5.0.dist-info/licenses/LICENSE
dymoprint-2.5.0.dist-info/RECORD
