Metadata-Version: 2.3
Name: dymoprint
Version: 2.5.0
Summary: Linux Software to print with LabelManager PnP from Dymo
Project-URL: Homepage, https://github.com/computerlyrik/dymoprint
Project-URL: source, https://github.com/computerlyrik/dymoprint
Project-URL: tracker, https://github.com/computerlyrik/dymoprint/issues
Author-email: "Sebastian J. Bronner" <waschtl@sbronner.com>
Maintainer-email: Ben Mares <services-dymoprint@tensorial.com>
License-Expression: Apache-2.0
License-File: LICENSE
Classifier: License :: OSI Approved :: Apache Software License
Classifier: Operating System :: POSIX :: Linux
Classifier: Programming Language :: Python :: 3.8
Classifier: Programming Language :: Python :: 3.9
Classifier: Programming Language :: Python :: 3.10
Classifier: Programming Language :: Python :: 3.11
Classifier: Programming Language :: Python :: 3.12
Classifier: Topic :: Printing
Requires-Python: <4,>=3.8
Requires-Dist: appdirs
Requires-Dist: importlib-metadata; python_version < '3.8'
Requires-Dist: pillow<11,>=8.1.2
Requires-Dist: pyqrcode<2,>=1.2.1
Requires-Dist: pyqt6
Requires-Dist: python-barcode<1,>=0.13.1
Requires-Dist: pyusb
